engeom-0.2.16.dist-info/METADATA
engeom-0.2.16.dist-info/WHEEL
engeom/__init__.py
engeom/_plot/__init__.py
engeom/_plot/common.py
engeom/_plot/matplotlib.py
engeom/_plot/pyvista.py
engeom/airfoil.pyi
engeom/airfoil/__init__.py
engeom/align.pyi
engeom/align/__init__.py
engeom/engeom.abi3.so
engeom/engeom.pyi
engeom/geom2.pyi
engeom/geom2/__init__.py
engeom/geom3.pyi
engeom/geom3/__init__.py
engeom/metrology.pyi
engeom/metrology/__init__.py
engeom/plot.py
engeom/raster3.pyi
engeom/raster3/__init__.py
engeom/sensors.pyi
engeom/sensors/__init__.py
engeom-0.2.16.dist-info/RECORD
